txtadv_nightly/BUILD_DESC.md
txtadv_nightly/__init__.py
txtadv_nightly/color/__init__.py
txtadv_nightly/commands/__init__.py
txtadv_nightly/file/__init__.py
txtadv_nightly/file/load.py
txtadv_nightly/file/save.py
txtadv_nightly/location/__init__.py
txtadv_nightly/messaging/__init__.py
txtadv_nightly/multiplayer/__init__.py
txtadv_nightly/multiplayer/recieve.py
txtadv_nightly/multiplayer/taw.proto
txtadv_nightly/multiplayer/taw_pb2.py
txtadv_nightly-110105103104116108121110105103104116108121.2.dist-info/LICENSE
txtadv_nightly-110105103104116108121110105103104116108121.2.dist-info/METADATA
txtadv_nightly-110105103104116108121110105103104116108121.2.dist-info/WHEEL
txtadv_nightly-110105103104116108121110105103104116108121.2.dist-info/RECORD
