Metadata-Version: 2.1
Name: txtadv-nightly
Version: 110105103104116108121110105103104116108121.2
Summary: The nightly version of txtadv, a feature-rich text adventure library!
License: MIT
Author: sdft
Author-email: averse.abfun@gmail.com
Requires-Python: >=3.10.0,<3.11
Classifier: License :: OSI Approved :: MIT License
Classifier: Programming Language :: Python :: 3
Classifier: Programming Language :: Python :: 3.10
